jtft.py
jtft-0.0.1.dist-info/licenses/LICENSE
jtft-0.0.1.dist-info/METADATA
jtft-0.0.1.dist-info/WHEEL
jtft-0.0.1.dist-info/top_level.txt
jtft-0.0.1.dist-info/RECORD
