Metadata-Version: 2.4
Name: jtft
Version: 0.0.1
Author: du7ec
Author-email: dutec6834@gmail.com
License-File: LICENSE
Requires-Dist: chardet
Dynamic: author
Dynamic: author-email
Dynamic: license-file
Dynamic: requires-dist
